{
    "id": "",
    "platform_url": "",
    "source_url": "",
    "app_name": "TOTAL",
    "platform_name": "TOTAL",
    "version": "",
    "users_count": 1833354,
    "processes_count": 164,
    "assemblies_count": 287,
    "comments_count": 56897,
    "users": 1775473,
    "participatory_processes": 977,
    "assemblies": 336,
    "comments": 53725,
    "meetings": 3874,
    "proposals": 35665,
    "accepted_proposals": 6785,
    "votes": 215970,
    "endorsements": 99019,
    "survey_answers": 620677,
    "results": 1343,
    "debates": 166
}