{
    "id": "",
    "platform_url": "",
    "source_url": "",
    "app_name": "TOTAL",
    "platform_name": "TOTAL",
    "version": "",
    "users_count": 1327226,
    "processes_count": 319,
    "assemblies_count": 697,
    "comments_count": 87619,
    "users": 1598197,
    "participatory_processes": 1585,
    "assemblies": 770,
    "comments": 90786,
    "meetings": 9200,
    "proposals": 78795,
    "accepted_proposals": 22638,
    "votes": 393226,
    "endorsements": 73287,
    "survey_answers": 812830,
    "results": 7997,
    "debates": 291
}