{
    "id": "",
    "platform_url": "",
    "source_url": "",
    "app_name": "TOTAL",
    "platform_name": "TOTAL",
    "version": "",
    "users_count": 1595874,
    "processes_count": 299,
    "assemblies_count": 772,
    "comments_count": 103634,
    "users": 1841278,
    "participatory_processes": 2078,
    "assemblies": 867,
    "comments": 114495,
    "meetings": 11855,
    "proposals": 98446,
    "accepted_proposals": 25577,
    "votes": 504258,
    "endorsements": 126111,
    "survey_answers": 1118286,
    "results": 8445,
    "debates": 249
}