{
    "id": "",
    "platform_url": "",
    "source_url": "",
    "app_name": "TOTAL",
    "platform_name": "TOTAL",
    "version": "",
    "users_count": 1534127,
    "processes_count": 287,
    "assemblies_count": 780,
    "comments_count": 105947,
    "users": 1652926,
    "participatory_processes": 1873,
    "assemblies": 886,
    "comments": 108320,
    "meetings": 9900,
    "proposals": 94866,
    "accepted_proposals": 26780,
    "votes": 451795,
    "endorsements": 112035,
    "survey_answers": 1127656,
    "results": 8098,
    "debates": 315
}