{
    "id": "",
    "platform_url": "",
    "source_url": "",
    "app_name": "TOTAL",
    "platform_name": "TOTAL",
    "version": "",
    "users_count": 1956462,
    "processes_count": 213,
    "assemblies_count": 531,
    "comments_count": 85255,
    "users": 1907475,
    "participatory_processes": 1889,
    "assemblies": 615,
    "comments": 92850,
    "meetings": 5730,
    "proposals": 74737,
    "accepted_proposals": 9476,
    "votes": 257707,
    "endorsements": 130454,
    "survey_answers": 1290025,
    "results": 1924,
    "debates": 276
}