{
    "id": "",
    "platform_url": "",
    "source_url": "",
    "app_name": "TOTAL",
    "platform_name": "TOTAL",
    "version": "",
    "users_count": 1433682,
    "processes_count": 312,
    "assemblies_count": 759,
    "comments_count": 100486,
    "users": 1767789,
    "participatory_processes": 1999,
    "assemblies": 852,
    "comments": 104829,
    "meetings": 11379,
    "proposals": 96756,
    "accepted_proposals": 25334,
    "votes": 497545,
    "endorsements": 95095,
    "survey_answers": 1142112,
    "results": 8316,
    "debates": 321
}