{
    "id": "",
    "platform_url": "",
    "source_url": "",
    "app_name": "TOTAL",
    "platform_name": "TOTAL",
    "version": "",
    "users_count": 1776985,
    "processes_count": 277,
    "assemblies_count": 954,
    "comments_count": 108973,
    "users": 1948443,
    "participatory_processes": 2219,
    "assemblies": 1053,
    "comments": 117905,
    "meetings": 12348,
    "proposals": 103670,
    "accepted_proposals": 25964,
    "votes": 508734,
    "endorsements": 130629,
    "survey_answers": 1285884,
    "results": 8703,
    "debates": 384
}