{
    "id": "",
    "platform_url": "",
    "source_url": "",
    "app_name": "TOTAL",
    "platform_name": "TOTAL",
    "version": "",
    "users_count": 1607325,
    "processes_count": 304,
    "assemblies_count": 776,
    "comments_count": 103772,
    "users": 1852393,
    "participatory_processes": 2086,
    "assemblies": 871,
    "comments": 114708,
    "meetings": 11889,
    "proposals": 100378,
    "accepted_proposals": 25591,
    "votes": 504261,
    "endorsements": 126844,
    "survey_answers": 1122630,
    "results": 8449,
    "debates": 249
}