{
    "id": "",
    "platform_url": "",
    "source_url": "",
    "app_name": "TOTAL",
    "platform_name": "TOTAL",
    "version": "",
    "users_count": 1994773,
    "processes_count": 284,
    "assemblies_count": 554,
    "comments_count": 84025,
    "users": 2056486,
    "participatory_processes": 2039,
    "assemblies": 637,
    "comments": 97399,
    "meetings": 5814,
    "proposals": 76766,
    "accepted_proposals": 10752,
    "votes": 274514,
    "endorsements": 134407,
    "survey_answers": 1264511,
    "results": 2236,
    "debates": 315
}