{
    "id": "",
    "platform_url": "",
    "source_url": "",
    "app_name": "TOTAL",
    "platform_name": "TOTAL",
    "version": "",
    "users_count": 633093,
    "processes_count": 31,
    "assemblies_count": 86,
    "comments_count": 30142,
    "users": 575526,
    "participatory_processes": 208,
    "assemblies": 81,
    "comments": 18168,
    "meetings": 600,
    "proposals": 8972,
    "accepted_proposals": 1571,
    "votes": 15375,
    "endorsements": 83140,
    "survey_answers": 485670,
    "results": 62,
    "debates": 18
}