{
    "id": "",
    "platform_url": "",
    "source_url": "",
    "app_name": "TOTAL",
    "platform_name": "TOTAL",
    "version": "",
    "users_count": 1893071,
    "processes_count": 287,
    "assemblies_count": 920,
    "comments_count": 108265,
    "users": 2063392,
    "participatory_processes": 2207,
    "assemblies": 1021,
    "comments": 123363,
    "meetings": 12381,
    "proposals": 102892,
    "accepted_proposals": 24922,
    "votes": 536611,
    "endorsements": 130063,
    "survey_answers": 1343180,
    "results": 8635,
    "debates": 366
}