{
    "id": "",
    "platform_url": "",
    "source_url": "",
    "app_name": "TOTAL",
    "platform_name": "TOTAL",
    "version": "",
    "users_count": 780996,
    "processes_count": 264,
    "assemblies_count": 933,
    "comments_count": 74962,
    "users": 796035,
    "participatory_processes": 1070,
    "assemblies": 910,
    "comments": 76251,
    "meetings": 7138,
    "proposals": 70344,
    "accepted_proposals": 19707,
    "votes": 379974,
    "endorsements": 67058,
    "survey_answers": 411587,
    "results": 7650,
    "debates": 351
}