{
    "id": "",
    "platform_url": "",
    "source_url": "",
    "app_name": "TOTAL",
    "platform_name": "TOTAL",
    "version": "",
    "users_count": 921515,
    "processes_count": 136,
    "assemblies_count": 164,
    "comments_count": 54678,
    "users": 947788,
    "participatory_processes": 741,
    "assemblies": 204,
    "comments": 51049,
    "meetings": 2402,
    "proposals": 27890,
    "accepted_proposals": 4672,
    "votes": 201279,
    "endorsements": 100612,
    "survey_answers": 576380,
    "results": 703,
    "debates": 103
}